hvppyautocapture/__init__.py
hvppyautocapture/api.py
hvppyautocapture/captureregionhelper.py
hvppyautocapture/engine.py
hvppyautocapture-0.0.1.dist-info/METADATA
hvppyautocapture-0.0.1.dist-info/WHEEL
hvppyautocapture-0.0.1.dist-info/entry_points.txt
hvppyautocapture-0.0.1.dist-info/RECORD
