Metadata-Version: 2.1
Name: hvppyautocapture
Version: 0.0.1
Project-URL: Homepage, https://github.com/hvppycoding/hvppyautocapture
Project-URL: Bug Tracker, https://github.com/hvppycoding/hvppyautocapture/issues
Author-email: hvppycoding <hvppycoding@gmail.com>
Classifier: Operating System :: OS Independent
Classifier: Programming Language :: Python :: 3
Requires-Python: >=3.7
Requires-Dist: pyautogui
Requires-Dist: pynput
